upload_sftp/__init__.py
upload_sftp/cli.py
upload_sftp/uploader.py
upload_sftp-0.1.0.dist-info/METADATA
upload_sftp-0.1.0.dist-info/WHEEL
upload_sftp-0.1.0.dist-info/entry_points.txt
upload_sftp-0.1.0.dist-info/top_level.txt
upload_sftp-0.1.0.dist-info/RECORD
