Metadata-Version: 2.4
Name: upload-sftp
Version: 0.1.0
Summary: Async SFTP uploader CLI with parallel uploads and retry logic
Requires-Python: >=3.13
Requires-Dist: asyncssh>=2.21.1
Requires-Dist: rich>=14.2.0
Requires-Dist: typer>=0.19.2
